pyspan/__init__.py
pyspan/compress.py
pyspan/convert_type.py
pyspan/convert_unit.py
pyspan/detect_errors.py
pyspan/detect_outliers.py
pyspan/format_dt.py
pyspan/handle_nulls.py
pyspan/logging_utils.py
pyspan/manual_rename_columns.py
pyspan/reduce_vif.py
pyspan/refine.py
pyspan/reformat.py
pyspan/remove.py
pyspan/remove_chars.py
pyspan/resize_dataset.py
pyspan/sample_data.py
pyspan/scale_data.py
pyspan/split_column.py
pyspan/state_management.py
pyspan/data/customer_sales_data.csv
pyspan-1.0.0.dist-info/LICENSE
pyspan-1.0.0.dist-info/METADATA
pyspan-1.0.0.dist-info/WHEEL
pyspan-1.0.0.dist-info/top_level.txt
pyspan-1.0.0.dist-info/RECORD
