Metadata-Version: 2.1
Name: pyspan
Version: 1.0.0
Summary: A Python package for efficient data cleaning and preprocessing
Home-page: https://github.com/pyspan24/pyspan_py.git
Author: Noor Surani, Amynah Reimoo
Author-email: nsurani@hotmail.com, amynahreimoo@gmail.com
License: MIT
Classifier: Programming Language :: Python :: 3
Classifier: License :: OSI Approved :: MIT License
Classifier: Operating System :: OS Independent
Requires-Python: >=3.8
License-File: LICENSE
Requires-Dist: numpy <3.0.0,>=1.23.2
Requires-Dist: pandas <=2.2.2
Requires-Dist: pyspellchecker ==0.8.1
Requires-Dist: scikit-learn <=1.6.1
Requires-Dist: statsmodels >=0.14.4
